{
  "collections": [
    {
      "slug": "limiar",
      "title": "LIMIAR",
      "date": "2026",
      "cover": "curva",
      "entries": [
        {
          "id": "curva",
          "file": "/mock/limiar.png",
          "alt": "Curva de concreto marcada por um recorte de luz no chão.",
          "width": 1024,
          "height": 1536
        },
        {
          "id": "janelas",
          "file": "/mock/eixo.png",
          "alt": "Janelas estreitas iluminam uma parede escura e o piso úmido.",
          "width": 1024,
          "height": 1536
        },
        {
          "id": "escada",
          "file": "/mock/vao.png",
          "alt": "Escada de concreto atravessada por uma faixa diagonal de luz.",
          "width": 1024,
          "height": 1536
        },
        {
          "id": "curva-aberta",
          "file": "/mock/limiar.png",
          "alt": "Recorte horizontal de uma curva de concreto iluminada.",
          "width": 1536,
          "height": 1024
        },
        {
          "id": "janelas-fechadas",
          "file": "/mock/eixo.png",
          "alt": "Detalhe quadrado de janelas estreitas sobre uma parede escura.",
          "width": 1200,
          "height": 1200
        },
        {
          "id": "escada-aberta",
          "file": "/mock/vao.png",
          "alt": "Recorte horizontal de uma escada de concreto atravessada por luz.",
          "width": 1536,
          "height": 1024
        }
      ]
    },
    {
      "slug": "eixo",
      "title": "EIXO",
      "date": "2025",
      "cover": "janelas",
      "entries": [
        {
          "id": "curva",
          "file": "/mock/limiar.png",
          "alt": "Curva de concreto marcada por um recorte de luz no chão.",
          "width": 1024,
          "height": 1536
        },
        {
          "id": "janelas",
          "file": "/mock/eixo.png",
          "alt": "Janelas estreitas iluminam uma parede escura e o piso úmido.",
          "width": 1024,
          "height": 1536
        },
        {
          "id": "escada",
          "file": "/mock/vao.png",
          "alt": "Escada de concreto atravessada por uma faixa diagonal de luz.",
          "width": 1024,
          "height": 1536
        },
        {
          "id": "curva-aberta",
          "file": "/mock/limiar.png",
          "alt": "Recorte horizontal de uma curva de concreto iluminada.",
          "width": 1536,
          "height": 1024
        },
        {
          "id": "janelas-fechadas",
          "file": "/mock/eixo.png",
          "alt": "Detalhe quadrado de janelas estreitas sobre uma parede escura.",
          "width": 1200,
          "height": 1200
        },
        {
          "id": "escada-aberta",
          "file": "/mock/vao.png",
          "alt": "Recorte horizontal de uma escada de concreto atravessada por luz.",
          "width": 1536,
          "height": 1024
        }
      ]
    },
    {
      "slug": "vao",
      "title": "VÃO",
      "date": "2024",
      "cover": "escada",
      "entries": [
        {
          "id": "curva",
          "file": "/mock/limiar.png",
          "alt": "Curva de concreto marcada por um recorte de luz no chão.",
          "width": 1024,
          "height": 1536
        },
        {
          "id": "janelas",
          "file": "/mock/eixo.png",
          "alt": "Janelas estreitas iluminam uma parede escura e o piso úmido.",
          "width": 1024,
          "height": 1536
        },
        {
          "id": "escada",
          "file": "/mock/vao.png",
          "alt": "Escada de concreto atravessada por uma faixa diagonal de luz.",
          "width": 1024,
          "height": 1536
        },
        {
          "id": "curva-aberta",
          "file": "/mock/limiar.png",
          "alt": "Recorte horizontal de uma curva de concreto iluminada.",
          "width": 1536,
          "height": 1024
        },
        {
          "id": "janelas-fechadas",
          "file": "/mock/eixo.png",
          "alt": "Detalhe quadrado de janelas estreitas sobre uma parede escura.",
          "width": 1200,
          "height": 1200
        },
        {
          "id": "escada-aberta",
          "file": "/mock/vao.png",
          "alt": "Recorte horizontal de uma escada de concreto atravessada por luz.",
          "width": 1536,
          "height": 1024
        }
      ]
    }
  ]
}
